{
  "type": "Feature",
  "properties": {
    "gn:admin1_code":"0.0",
    "gn:asciiname":"Petit Gouli",
    "gn:country_code":"NC",
    "gn:dem":48,
    "gn:feature_class":"P",
    "gn:feature_code":"PPL",
    "gn:name":"Petit Gouli",
    "gn:population":0,
    "gn:timezone":"Pacific/Noumea",
    "iso:country":"NC",
    "wof:name":"Petit Gouli",
    "wof:placetype":"locality"
},
  "geometry": {"coordinates":[165.83333000000005,-21.65],"type":"Point"}
}