{
  "type": "Feature",
  "properties": {
    "gn:country":"NC",
    "gn:fcode":"PPL",
    "gn:pop":24680,
    "iso:country":"NC",
    "name:bre_x_preferred":[
        "Le Mont-Dore"
    ],
    "name:cat_x_preferred":[
        "Montdaur"
    ],
    "name:ceb_x_preferred":[
        "Mont-Dore"
    ],
    "name:ces_x_preferred":[
        "Mont-Dore"
    ],
    "name:deu_x_preferred":[
        "Mont-Dore"
    ],
    "name:eus_x_preferred":[
        "Le Mont-Dore"
    ],
    "name:fra_x_preferred":[
        "Mont-Dore"
    ],
    "name:hun_x_preferred":[
        "Le Mont-Dore"
    ],
    "name:ita_x_preferred":[
        "Mont-Dore"
    ],
    "name:jpn_x_preferred":[
        "\u30e2\u30f3\uff1d\u30c9\u30fc\u30eb"
    ],
    "name:lat_x_preferred":[
        "Le Mont-Dore"
    ],
    "name:mlg_x_preferred":[
        "Le Mont-Dore"
    ],
    "name:msa_x_preferred":[
        "Mont-Dore"
    ],
    "name:nld_x_preferred":[
        "Mont-Dore"
    ],
    "name:oci_x_preferred":[
        "Mont D\u00f2r"
    ],
    "name:pms_x_preferred":[
        "Le Mont-Dore"
    ],
    "name:pol_x_preferred":[
        "Mont-Dore"
    ],
    "name:por_x_preferred":[
        "Mont-Dore"
    ],
    "name:ron_x_preferred":[
        "Mont-Dore"
    ],
    "name:rus_x_preferred":[
        "\u041c\u043e\u043d-\u0414\u043e\u0440"
    ],
    "name:slk_x_preferred":[
        "Mont-Dore"
    ],
    "name:spa_x_preferred":[
        "Mont-Dore"
    ],
    "name:swe_x_preferred":[
        "Mont-Dore"
    ],
    "name:ukr_x_preferred":[
        "\u041c\u043e\u043d-\u0414\u043e\u0440"
    ],
    "name:uzb_x_preferred":[
        "Mont-Dore"
    ],
    "name:vie_x_preferred":[
        "Mont-Dore"
    ],
    "name:vol_x_preferred":[
        "Mont-Dore"
    ],
    "name:war_x_preferred":[
        "Mont-Dore"
    ],
    "name:zho_x_preferred":[
        "\u8499\u591a\u5c14"
    ],
    "qs:name":"Mont-Dore",
    "qs:photos_9r":0,
    "qs:photos_sr":0,
    "qs:pop_sr":"7",
    "wof:name":"Mont-Dore",
    "wof:placetype":"locality",
    "wof:population":24680
},
  "geometry": {"coordinates":[166.58332999999999,-22.28333],"type":"Point"}
}