{
  "type": "Feature",
  "properties": {
    "gn:country":"NC",
    "gn:fcode":"PPL",
    "gn:pop":24680,
    "iso:country":"NC",
    "qs:name":"Mont-Dore",
    "qs:photos_9r":0,
    "qs:photos_sr":0,
    "qs:pop_sr":"7",
    "wof:name":"Mont-Dore",
    "wof:placetype":"locality",
    "wof:population":24680
},
  "geometry": {"coordinates":[166.58332999999999,-22.28333],"type":"Point"}
}