{
  "type": "Feature",
  "properties": {
    "gn:admin1_code":"0.0",
    "gn:asciiname":"Goa",
    "gn:country_code":"NC",
    "gn:dem":76,
    "gn:feature_class":"P",
    "gn:feature_code":"PPL",
    "gn:name":"Goa",
    "gn:population":0,
    "gn:timezone":"Pacific/Noumea",
    "iso:country":"NC",
    "wof:name":"Goa",
    "wof:placetype":"locality"
},
  "geometry": {"coordinates":[165.30000000000001,-21.11667000000001],"type":"Point"}
}