{
  "type": "Feature",
  "properties": {
    "gn:admin1_code":"0.0",
    "gn:asciiname":"Saint-Paul",
    "gn:country_code":"NC",
    "gn:dem":266,
    "gn:feature_class":"P",
    "gn:feature_code":"PPL",
    "gn:name":"Saint-Paul",
    "gn:population":0,
    "gn:timezone":"Pacific/Noumea",
    "iso:country":"NC",
    "wof:name":"Saint-Paul",
    "wof:placetype":"locality"
},
  "geometry": {"coordinates":[164.53333000000001,-20.35],"type":"Point"}
}