{
  "type": "Feature",
  "properties": {
    "gn:admin1_code":"0.0",
    "gn:asciiname":"Taanlo",
    "gn:country_code":"NC",
    "gn:dem":11,
    "gn:feature_class":"P",
    "gn:feature_code":"PPL",
    "gn:name":"Taanl\u00f4",
    "gn:population":0,
    "gn:timezone":"Pacific/Noumea",
    "iso:country":"NC",
    "wof:name":"Taanlo",
    "wof:placetype":"locality"
},
  "geometry": {"coordinates":[163.93333000000001,-20.01667],"type":"Point"}
}