{
  "type": "Feature",
  "properties": {
    "gn:admin1_code":"0.0",
    "gn:asciiname":"Paraoua",
    "gn:country_code":"NC",
    "gn:dem":10,
    "gn:feature_class":"P",
    "gn:feature_code":"PPL",
    "gn:name":"Paraoua",
    "gn:population":0,
    "gn:timezone":"Pacific/Noumea",
    "iso:country":"NC",
    "wof:name":"Paraoua",
    "wof:placetype":"locality"
},
  "geometry": {"coordinates":[164.44999999999999,-20.35],"type":"Point"}
}