{
  "type": "Feature",
  "properties": {
    "gn:admin1_code":"0.0",
    "gn:asciiname":"Nessapoue",
    "gn:country_code":"NC",
    "gn:dem":125,
    "gn:feature_class":"P",
    "gn:feature_code":"PPL",
    "gn:name":"N\u00e9ssapou\u00e9",
    "gn:population":0,
    "gn:timezone":"Pacific/Noumea",
    "iso:country":"NC",
    "wof:name":"Nessapoue",
    "wof:placetype":"locality"
},
  "geometry": {"coordinates":[165.36667,-20.96667],"type":"Point"}
}