{
  "type": "Feature",
  "properties": {
    "gn:admin1_code":"0.0",
    "gn:asciiname":"Yate-Village",
    "gn:cc2":"NC",
    "gn:country_code":"NC",
    "gn:dem":312,
    "gn:feature_class":"P",
    "gn:feature_code":"PPL",
    "gn:name":"Yat\u00e9-Village",
    "gn:population":0,
    "gn:timezone":"Pacific/Noumea",
    "iso:country":"NC",
    "name:und_x_variant":[
        "Iate",
        "Yat\u00e9",
        "Yat\u00e9-Village"
    ],
    "wof:name":"Yate-Village",
    "wof:placetype":"locality"
},
  "geometry": {"coordinates":[166.90000000000001,-22.15],"type":"Point"}
}