{
  "type": "Feature",
  "properties": {
    "gn:admin1_code":"0.0",
    "gn:asciiname":"Tomo",
    "gn:country_code":"NC",
    "gn:dem":-9999,
    "gn:feature_class":"P",
    "gn:feature_code":"PPL",
    "gn:name":"Tomo",
    "gn:population":0,
    "gn:timezone":"Pacific/Noumea",
    "iso:country":"NC",
    "name:ceb_x_preferred":[
        "Tomo"
    ],
    "name:ita_x_preferred":[
        "Tomo"
    ],
    "name:nld_x_preferred":[
        "Tomo"
    ],
    "name:spa_x_preferred":[
        "Tomo"
    ],
    "name:swe_x_preferred":[
        "Tomo"
    ],
    "name:tgl_x_preferred":[
        "Tomo"
    ],
    "wof:name":"Tomo",
    "wof:placetype":"locality"
},
  "geometry": {"coordinates":[166.13333,-21.96667],"type":"Point"}
}