{
  "type": "Feature",
  "properties": {
    "gn:admin1_code":"0.0",
    "gn:asciiname":"Nanawa",
    "gn:country_code":"NC",
    "gn:dem":1,
    "gn:feature_class":"P",
    "gn:feature_code":"PPL",
    "gn:name":"Nanawa",
    "gn:population":0,
    "gn:timezone":"Pacific/Noumea",
    "iso:country":"NC",
    "name:eus_x_preferred":[
        "Nanawa"
    ],
    "name:grn_x_preferred":[
        "Nanawa"
    ],
    "name:ita_x_preferred":[
        "Nanawa"
    ],
    "name:pol_x_preferred":[
        "Nanawa"
    ],
    "name:por_x_preferred":[
        "Nanawa"
    ],
    "name:spa_x_preferred":[
        "Nanawa"
    ],
    "name:ukr_x_preferred":[
        "\u041d\u0430\u043d\u0430\u0432\u0430"
    ],
    "name:zho_x_preferred":[
        "\u7d0d\u7d0d\u74e6"
    ],
    "wof:name":"Nanawa",
    "wof:placetype":"locality"
},
  "geometry": {"coordinates":[167.09999999999999,-20.76667],"type":"Point"}
}