{
  "type": "Feature",
  "properties": {
    "gn:admin1_code":"0.0",
    "gn:asciiname":"Nanawa",
    "gn:country_code":"NC",
    "gn:dem":1,
    "gn:feature_class":"P",
    "gn:feature_code":"PPL",
    "gn:name":"Nanawa",
    "gn:population":0,
    "gn:timezone":"Pacific/Noumea",
    "iso:country":"NC",
    "wof:name":"Nanawa",
    "wof:placetype":"locality"
},
  "geometry": {"coordinates":[167.09999999999999,-20.76667],"type":"Point"}
}