{
  "type": "Feature",
  "properties": {
    "gn:admin1_code":"0.0",
    "gn:asciiname":"Kopelia",
    "gn:country_code":"NC",
    "gn:dem":51,
    "gn:feature_class":"P",
    "gn:feature_code":"PPL",
    "gn:name":"Kop\u00e9lia",
    "gn:population":0,
    "gn:timezone":"Pacific/Noumea",
    "iso:country":"NC",
    "wof:name":"Kopelia",
    "wof:placetype":"locality"
},
  "geometry": {"coordinates":[166.01667,-21.56667],"type":"Point"}
}