{
  "type": "Feature",
  "properties": {
    "gn:admin1_code":"0.0",
    "gn:asciiname":"Ognat",
    "gn:cc2":"NC",
    "gn:country_code":"NC",
    "gn:dem":12,
    "gn:feature_class":"P",
    "gn:feature_code":"PPL",
    "gn:name":"Ognat",
    "gn:population":0,
    "gn:timezone":"Pacific/Noumea",
    "iso:country":"NC",
    "name:und_x_variant":[
        "Saint-Thomas",
        "Ognat",
        "Ohnyat"
    ],
    "wof:name":"Ognat",
    "wof:placetype":"locality"
},
  "geometry": {"coordinates":[166.65236000000004,-20.47635],"type":"Point"}
}