{
  "type": "Feature",
  "properties": {
    "gn:admin1_code":"0.0",
    "gn:asciiname":"Oualanga",
    "gn:country_code":"NC",
    "gn:dem":49,
    "gn:feature_class":"P",
    "gn:feature_code":"PPL",
    "gn:name":"Oualanga",
    "gn:population":0,
    "gn:timezone":"Pacific/Noumea",
    "iso:country":"NC",
    "wof:name":"Oualanga",
    "wof:placetype":"locality"
},
  "geometry": {"coordinates":[164.43333000000001,-20.63333],"type":"Point"}
}