{
  "type": "Feature",
  "properties": {
    "gn:admin1_code":"0.0",
    "gn:asciiname":"Toul",
    "gn:country_code":"NC",
    "gn:dem":42,
    "gn:feature_class":"P",
    "gn:feature_code":"PPL",
    "gn:name":"Toul",
    "gn:population":0,
    "gn:timezone":"Pacific/Noumea",
    "iso:country":"NC",
    "name:ara_x_preferred":[
        "\u062a\u0648\u0644"
    ],
    "name:bre_x_preferred":[
        "Toul"
    ],
    "name:bul_x_preferred":[
        "\u0422\u0443\u043b"
    ],
    "name:cat_x_preferred":[
        "Toul"
    ],
    "name:ceb_x_preferred":[
        "Toul"
    ],
    "name:ces_x_preferred":[
        "Toul"
    ],
    "name:deu_x_preferred":[
        "Toul"
    ],
    "name:epo_x_preferred":[
        "Toul"
    ],
    "name:est_x_preferred":[
        "Toul"
    ],
    "name:eus_x_preferred":[
        "Toul"
    ],
    "name:fas_x_preferred":[
        "\u062a\u0648\u0644"
    ],
    "name:fin_x_preferred":[
        "Toul"
    ],
    "name:fra_x_preferred":[
        "Toul"
    ],
    "name:hun_x_preferred":[
        "Toul"
    ],
    "name:ita_x_preferred":[
        "Toul"
    ],
    "name:jpn_x_preferred":[
        "\u30c8\u30a5\u30fc\u30eb"
    ],
    "name:kaz_x_preferred":[
        "\u0422\u0443\u043b\u044c"
    ],
    "name:kor_x_preferred":[
        "\ud234"
    ],
    "name:lat_x_preferred":[
        "Tullum Leucorum"
    ],
    "name:lit_x_preferred":[
        "Tulis"
    ],
    "name:ltz_x_preferred":[
        "Toul"
    ],
    "name:msa_x_preferred":[
        "Toul"
    ],
    "name:nld_x_preferred":[
        "Toul"
    ],
    "name:nno_x_preferred":[
        "Toul"
    ],
    "name:nor_x_preferred":[
        "Toul"
    ],
    "name:oci_x_preferred":[
        "Toul"
    ],
    "name:pms_x_preferred":[
        "Toul"
    ],
    "name:pol_x_preferred":[
        "Toul"
    ],
    "name:por_x_preferred":[
        "Toul"
    ],
    "name:ron_x_preferred":[
        "Toul"
    ],
    "name:rus_x_preferred":[
        "\u0422\u0443\u043b\u044c"
    ],
    "name:slk_x_preferred":[
        "Toul"
    ],
    "name:slv_x_preferred":[
        "Toul"
    ],
    "name:spa_x_preferred":[
        "Toul"
    ],
    "name:swe_x_preferred":[
        "Toul"
    ],
    "name:tur_x_preferred":[
        "Toul"
    ],
    "name:ukr_x_preferred":[
        "\u0422\u0443\u043b\u044c"
    ],
    "name:urd_x_preferred":[
        "\u062a\u0648\u0644"
    ],
    "name:uzb_x_preferred":[
        "Toul"
    ],
    "name:vie_x_preferred":[
        "Toul"
    ],
    "name:vol_x_preferred":[
        "Toul"
    ],
    "name:war_x_preferred":[
        "Toul"
    ],
    "name:zho_x_preferred":[
        "\u56fe\u52d2"
    ],
    "wof:name":"Toul",
    "wof:placetype":"locality"
},
  "geometry": {"coordinates":[167.41666999999995,-21.08333],"type":"Point"}
}