{
  "type": "Feature",
  "properties": {
    "gn:admin1_code":"0.0",
    "gn:asciiname":"Toul",
    "gn:country_code":"NC",
    "gn:dem":42,
    "gn:feature_class":"P",
    "gn:feature_code":"PPL",
    "gn:name":"Toul",
    "gn:population":0,
    "gn:timezone":"Pacific/Noumea",
    "iso:country":"NC",
    "wof:name":"Toul",
    "wof:placetype":"locality"
},
  "geometry": {"coordinates":[167.41666999999995,-21.08333],"type":"Point"}
}