{
  "type": "Feature",
  "properties": {
    "gn:admin1_code":"0.0",
    "gn:asciiname":"Haouli",
    "gn:country_code":"NC",
    "gn:dem":177,
    "gn:feature_class":"P",
    "gn:feature_code":"PPL",
    "gn:name":"Haouli",
    "gn:population":0,
    "gn:timezone":"Pacific/Noumea",
    "iso:country":"NC",
    "wof:name":"Haouli",
    "wof:placetype":"locality"
},
  "geometry": {"coordinates":[165.84999999999999,-21.53333],"type":"Point"}
}