{
  "type": "Feature",
  "properties": {
    "gn:admin1_code":"0.0",
    "gn:asciiname":"Ouingo",
    "gn:country_code":"NC",
    "gn:dem":124,
    "gn:feature_class":"P",
    "gn:feature_code":"PPL",
    "gn:name":"Ouingo",
    "gn:population":0,
    "gn:timezone":"Pacific/Noumea",
    "iso:country":"NC",
    "wof:name":"Ouingo",
    "wof:placetype":"locality"
},
  "geometry": {"coordinates":[165.51667,-21.28333],"type":"Point"}
}