{
  "type": "Feature",
  "properties": {
    "gn:admin1_code":"0.0",
    "gn:asciiname":"Mea-Mebara",
    "gn:cc2":"NC",
    "gn:country_code":"NC",
    "gn:dem":112,
    "gn:feature_class":"P",
    "gn:feature_code":"PPL",
    "gn:name":"M\u00e9a-M\u00e9bara",
    "gn:population":0,
    "gn:timezone":"Pacific/Noumea",
    "iso:country":"NC",
    "name:und_x_variant":[
        "M\u00e9a",
        "M\u00e9a-M\u00e9bara"
    ],
    "wof:name":"Mea-Mebara",
    "wof:placetype":"locality"
},
  "geometry": {"coordinates":[165.78333000000001,-21.46667],"type":"Point"}
}