{
  "type": "Feature",
  "properties": {
    "gn:admin1_code":"0.0",
    "gn:asciiname":"Koh",
    "gn:country_code":"NC",
    "gn:dem":103,
    "gn:feature_class":"P",
    "gn:feature_code":"PPL",
    "gn:name":"Koh",
    "gn:population":0,
    "gn:timezone":"Pacific/Noumea",
    "iso:country":"NC",
    "wof:name":"Koh",
    "wof:placetype":"locality"
},
  "geometry": {"coordinates":[165.83333000000005,-21.53333],"type":"Point"}
}