{
  "type": "Feature",
  "properties": {
    "gn:admin1_code":"0.0",
    "gn:asciiname":"Le Cresson",
    "gn:country_code":"NC",
    "gn:dem":127,
    "gn:feature_class":"P",
    "gn:feature_code":"PPL",
    "gn:name":"Le Cresson",
    "gn:population":0,
    "gn:timezone":"Pacific/Noumea",
    "iso:country":"NC",
    "wof:name":"Le Cresson",
    "wof:placetype":"locality"
},
  "geometry": {"coordinates":[164.30000000000001,-20.48333],"type":"Point"}
}