{
  "type": "Feature",
  "properties": {
    "gn:admin1_code":"2.0",
    "gn:admin2_code":"98817.0",
    "gn:asciiname":"Plum",
    "gn:country_code":"NC",
    "gn:dem":53,
    "gn:feature_class":"P",
    "gn:feature_code":"PPL",
    "gn:name":"Plum",
    "gn:population":0,
    "gn:timezone":"Pacific/Noumea",
    "iso:country":"NC",
    "wof:name":"Plum",
    "wof:placetype":"locality"
},
  "geometry": {"coordinates":[166.61439999999999,-22.27226],"type":"Point"}
}