{
  "type": "Feature",
  "properties": {
    "gn:admin1_code":"0.0",
    "gn:asciiname":"Bouelas",
    "gn:country_code":"NC",
    "gn:dem":191,
    "gn:feature_class":"P",
    "gn:feature_code":"PPL",
    "gn:name":"Bou\u00e9las",
    "gn:population":0,
    "gn:timezone":"Pacific/Noumea",
    "iso:country":"NC",
    "wof:name":"Bouelas",
    "wof:placetype":"locality"
},
  "geometry": {"coordinates":[164.55000000000001,-20.53333],"type":"Point"}
}