{
  "type": "Feature",
  "properties": {
    "gn:admin1_code":"0.0",
    "gn:asciiname":"Neya",
    "gn:country_code":"NC",
    "gn:dem":26,
    "gn:feature_class":"P",
    "gn:feature_code":"PPL",
    "gn:name":"N\u00e9ya",
    "gn:population":0,
    "gn:timezone":"Pacific/Noumea",
    "iso:country":"NC",
    "wof:name":"Neya",
    "wof:placetype":"locality"
},
  "geometry": {"coordinates":[165.58333000000005,-21.21667],"type":"Point"}
}