{
  "type": "Feature",
  "properties": {
    "gn:admin1_code":"0.0",
    "gn:asciiname":"Tiare",
    "gn:country_code":"NC",
    "gn:dem":4,
    "gn:feature_class":"P",
    "gn:feature_code":"PPL",
    "gn:name":"Tiar\u00e9",
    "gn:population":0,
    "gn:timezone":"Pacific/Noumea",
    "iso:country":"NC",
    "wof:name":"Tiare",
    "wof:placetype":"locality"
},
  "geometry": {"coordinates":[166.28333000000001,-22.16667],"type":"Point"}
}