{
  "type": "Feature",
  "properties": {
    "gn:admin1_code":"0.0",
    "gn:asciiname":"Lot",
    "gn:country_code":"NC",
    "gn:dem":8,
    "gn:feature_class":"P",
    "gn:feature_code":"PPL",
    "gn:name":"Lot",
    "gn:population":0,
    "gn:timezone":"Pacific/Noumea",
    "iso:country":"NC",
    "wof:name":"Lot",
    "wof:placetype":"locality"
},
  "geometry": {"coordinates":[167.84999999999999,-21.38333],"type":"Point"}
}