{
  "type": "Feature",
  "properties": {
    "gn:admin1_code":"0.0",
    "gn:asciiname":"Pinjen",
    "gn:country_code":"NC",
    "gn:dem":10,
    "gn:feature_class":"P",
    "gn:feature_code":"PPL",
    "gn:name":"Pinjen",
    "gn:population":0,
    "gn:timezone":"Pacific/Noumea",
    "iso:country":"NC",
    "wof:name":"Pinjen",
    "wof:placetype":"locality"
},
  "geometry": {"coordinates":[164.76667,-21.05],"type":"Point"}
}