{
  "type": "Feature",
  "properties": {
    "gn:admin1_code":"0.0",
    "gn:asciiname":"Gohapin",
    "gn:country_code":"NC",
    "gn:dem":142,
    "gn:feature_class":"P",
    "gn:feature_code":"PPL",
    "gn:name":"Gohapin",
    "gn:population":0,
    "gn:timezone":"Pacific/Noumea",
    "iso:country":"NC",
    "wof:name":"Gohapin",
    "wof:placetype":"locality"
},
  "geometry": {"coordinates":[165.27269999999999,-21.21866],"type":"Point"}
}