{
  "type": "Feature",
  "properties": {
    "gn:admin1_code":"0.0",
    "gn:asciiname":"Haute Tamoa",
    "gn:country_code":"NC",
    "gn:dem":95,
    "gn:feature_class":"P",
    "gn:feature_code":"PPL",
    "gn:name":"Haute Tamoa",
    "gn:population":0,
    "gn:timezone":"Pacific/Noumea",
    "iso:country":"NC",
    "wof:name":"Haute Tamoa",
    "wof:placetype":"locality"
},
  "geometry": {"coordinates":[166.30000000000001,-22.05],"type":"Point"}
}