{
  "type": "Feature",
  "properties": {
    "gn:admin1_code":"0.0",
    "gn:asciiname":"Noeli",
    "gn:country_code":"NC",
    "gn:dem":96,
    "gn:feature_class":"P",
    "gn:feature_code":"PPL",
    "gn:name":"No\u00e9li",
    "gn:population":0,
    "gn:timezone":"Pacific/Noumea",
    "iso:country":"NC",
    "wof:name":"Noeli",
    "wof:placetype":"locality"
},
  "geometry": {"coordinates":[164.94999999999999,-21.01667],"type":"Point"}
}