{
  "type": "Feature",
  "properties": {
    "gn:admin1_code":"0.0",
    "gn:asciiname":"Lekine",
    "gn:cc2":"NC",
    "gn:country_code":"NC",
    "gn:dem":8,
    "gn:feature_class":"P",
    "gn:feature_code":"PPL",
    "gn:name":"L\u00e9kine",
    "gn:population":0,
    "gn:timezone":"Pacific/Noumea",
    "iso:country":"NC",
    "name:und_x_variant":[
        "Lekia",
        "Lekin",
        "L\u00e9kine"
    ],
    "wof:name":"Lekine",
    "wof:placetype":"locality"
},
  "geometry": {"coordinates":[166.48926,-20.69408],"type":"Point"}
}