{
  "type": "Feature",
  "properties": {
    "gn:admin1_code":"0.0",
    "gn:asciiname":"Namelagat",
    "gn:country_code":"NC",
    "gn:dem":46,
    "gn:feature_class":"P",
    "gn:feature_code":"PPL",
    "gn:name":"Nam\u00e9lagat",
    "gn:population":0,
    "gn:timezone":"Pacific/Noumea",
    "iso:country":"NC",
    "wof:name":"Namelagat",
    "wof:placetype":"locality"
},
  "geometry": {"coordinates":[167.35173,-21.09879],"type":"Point"}
}