{
  "type": "Feature",
  "properties": {
    "gn:admin1_code":"0.0",
    "gn:asciiname":"Miramas",
    "gn:country_code":"NC",
    "gn:dem":55,
    "gn:feature_class":"P",
    "gn:feature_code":"PPL",
    "gn:name":"Miramas",
    "gn:population":0,
    "gn:timezone":"Pacific/Noumea",
    "iso:country":"NC",
    "name:azb_x_preferred":[
        "\u0645\u06cc\u0631\u0645\u0627"
    ],
    "name:cat_x_preferred":[
        "Miram\u00e0s"
    ],
    "name:ceb_x_preferred":[
        "Miramas"
    ],
    "name:deu_x_preferred":[
        "Miramas"
    ],
    "name:epo_x_preferred":[
        "Miramas"
    ],
    "name:eus_x_preferred":[
        "Miramas"
    ],
    "name:fas_x_preferred":[
        "\u0645\u06cc\u0631\u0645\u0627"
    ],
    "name:fin_x_preferred":[
        "Miramas"
    ],
    "name:fra_x_preferred":[
        "Miramas"
    ],
    "name:hun_x_preferred":[
        "Miramas"
    ],
    "name:hye_x_preferred":[
        "\u0544\u056b\u0580\u0561\u0574\u0561\u057d"
    ],
    "name:ilo_x_preferred":[
        "Miramas"
    ],
    "name:ita_x_preferred":[
        "Miramas"
    ],
    "name:jpn_x_preferred":[
        "\u30df\u30e9\u30de"
    ],
    "name:kor_x_preferred":[
        "\ubbf8\ub77c\ub9c8"
    ],
    "name:lat_x_preferred":[
        "Miramas"
    ],
    "name:lmo_x_preferred":[
        "Miramas"
    ],
    "name:ltz_x_preferred":[
        "Miramas"
    ],
    "name:mlg_x_preferred":[
        "Miramas"
    ],
    "name:msa_x_preferred":[
        "Miramas"
    ],
    "name:nld_x_preferred":[
        "Miramas"
    ],
    "name:nor_x_preferred":[
        "Miramas"
    ],
    "name:oci_x_preferred":[
        "Miram\u00e0s"
    ],
    "name:pms_x_preferred":[
        "Miramas"
    ],
    "name:pol_x_preferred":[
        "Miramas"
    ],
    "name:por_x_preferred":[
        "Miramas"
    ],
    "name:ron_x_preferred":[
        "Miramas"
    ],
    "name:rus_x_preferred":[
        "\u041c\u0438\u0440\u0430\u043c\u0430\u0441"
    ],
    "name:slk_x_preferred":[
        "Miramas"
    ],
    "name:slv_x_preferred":[
        "Miramas"
    ],
    "name:spa_x_preferred":[
        "Miramas"
    ],
    "name:srp_x_preferred":[
        "\u041c\u0438\u0440\u0430\u043c\u0430\u0441"
    ],
    "name:swa_x_preferred":[
        "Miramas"
    ],
    "name:swe_x_preferred":[
        "Miramas"
    ],
    "name:tur_x_preferred":[
        "Miramas"
    ],
    "name:ukr_x_preferred":[
        "\u041c\u0456\u0440\u0430\u043c\u0430\u0441"
    ],
    "name:vie_x_preferred":[
        "Miramas"
    ],
    "name:vol_x_preferred":[
        "Miramas"
    ],
    "name:war_x_preferred":[
        "Miramas"
    ],
    "name:zho_x_preferred":[
        "\u7c73\u62c9\u9a6c\u65af"
    ],
    "wof:name":"Miramas",
    "wof:placetype":"locality"
},
  "geometry": {"coordinates":[167.98333,-21.48333],"type":"Point"}
}