{
  "type": "Feature",
  "properties": {
    "gn:admin1_code":"0.0",
    "gn:asciiname":"Cradji",
    "gn:country_code":"NC",
    "gn:dem":62,
    "gn:feature_class":"P",
    "gn:feature_code":"PPL",
    "gn:name":"Cradji",
    "gn:population":0,
    "gn:timezone":"Pacific/Noumea",
    "iso:country":"NC",
    "wof:name":"Cradji",
    "wof:placetype":"locality"
},
  "geometry": {"coordinates":[165.15000000000001,-21.31667],"type":"Point"}
}