{
  "type": "Feature",
  "properties": {
    "gn:admin1_code":"0.0",
    "gn:asciiname":"Ho",
    "gn:country_code":"NC",
    "gn:dem":76,
    "gn:feature_class":"P",
    "gn:feature_code":"PPL",
    "gn:name":"H\u00f4",
    "gn:population":0,
    "gn:timezone":"Pacific/Noumea",
    "iso:country":"NC",
    "name:ben_x_preferred":[
        "\u09b9\u09cb"
    ],
    "name:ell_x_preferred":[
        "\u03a7\u03bf"
    ],
    "name:heb_x_preferred":[
        "\u05d4\u05d5"
    ],
    "name:hin_x_preferred":[
        "\u0939\u094b"
    ],
    "name:hun_x_preferred":[
        "Ho"
    ],
    "name:ind_x_preferred":[
        "Ho"
    ],
    "name:spa_x_preferred":[
        "Ho"
    ],
    "name:tur_x_preferred":[
        "Ho"
    ],
    "name:vie_x_preferred":[
        "Ho"
    ],
    "wof:name":"Ho",
    "wof:placetype":"locality"
},
  "geometry": {"coordinates":[165.53333000000001,-21.18333],"type":"Point"}
}