{
  "type": "Feature",
  "properties": {
    "gn:admin1_code":"0.0",
    "gn:asciiname":"Poueo",
    "gn:cc2":"NC",
    "gn:country_code":"NC",
    "gn:dem":24,
    "gn:feature_class":"P",
    "gn:feature_code":"PPL",
    "gn:name":"Pou\u00e9o",
    "gn:population":0,
    "gn:timezone":"Pacific/Noumea",
    "iso:country":"NC",
    "name:und_x_variant":[
        "Pon\u00e9o",
        "Pou\u00e9o"
    ],
    "wof:name":"Poueo",
    "wof:placetype":"locality"
},
  "geometry": {"coordinates":[165.51667,-21.51667],"type":"Point"}
}