{
  "type": "Feature",
  "properties": {
    "gn:admin1_code":"0.0",
    "gn:asciiname":"Balagam",
    "gn:cc2":"NC",
    "gn:country_code":"NC",
    "gn:dem":7,
    "gn:feature_class":"P",
    "gn:feature_code":"PPL",
    "gn:name":"Balagam",
    "gn:population":0,
    "gn:timezone":"Pacific/Noumea",
    "iso:country":"NC",
    "name:guj_x_preferred":[
        "\u0aac\u0abe\u0ab2\u0abe\u0a97\u0abe\u0aae"
    ],
    "name:und_x_variant":[
        "Balagham",
        "Balagam"
    ],
    "wof:name":"Balagam",
    "wof:placetype":"locality"
},
  "geometry": {"coordinates":[164.40000000000001,-20.35],"type":"Point"}
}