{
  "type": "Feature",
  "properties": {
    "gn:admin1_code":"0.0",
    "gn:asciiname":"Ouenia",
    "gn:country_code":"NC",
    "gn:dem":158,
    "gn:feature_class":"P",
    "gn:feature_code":"PPL",
    "gn:name":"Ou\u00e9nia",
    "gn:population":0,
    "gn:timezone":"Pacific/Noumea",
    "iso:country":"NC",
    "wof:name":"Ouenia",
    "wof:placetype":"locality"
},
  "geometry": {"coordinates":[164.51667,-20.51667],"type":"Point"}
}