{
  "type": "Feature",
  "properties": {
    "gn:admin1_code":"0.0",
    "gn:asciiname":"Wassadieuhu",
    "gn:country_code":"NC",
    "gn:dem":15,
    "gn:feature_class":"P",
    "gn:feature_code":"PPL",
    "gn:name":"Wassadieuhu",
    "gn:population":0,
    "gn:timezone":"Pacific/Noumea",
    "iso:country":"NC",
    "wof:name":"Wassadieuhu",
    "wof:placetype":"locality"
},
  "geometry": {"coordinates":[166.55000000000001,-20.65],"type":"Point"}
}