{
  "type": "Feature",
  "properties": {
    "gn:admin1_code":"0.0",
    "gn:asciiname":"Ni",
    "gn:country_code":"NC",
    "gn:dem":202,
    "gn:feature_class":"P",
    "gn:feature_code":"PPL",
    "gn:name":"Ni",
    "gn:population":0,
    "gn:timezone":"Pacific/Noumea",
    "iso:country":"NC",
    "wof:name":"Ni",
    "wof:placetype":"locality"
},
  "geometry": {"coordinates":[165.48333,-21.43333],"type":"Point"}
}