{
  "type": "Feature",
  "properties": {
    "gn:admin1_code":"0.0",
    "gn:asciiname":"Neoua",
    "gn:country_code":"NC",
    "gn:dem":213,
    "gn:feature_class":"P",
    "gn:feature_code":"PPL",
    "gn:name":"N\u00e9oua",
    "gn:population":0,
    "gn:timezone":"Pacific/Noumea",
    "iso:country":"NC",
    "wof:name":"Neoua",
    "wof:placetype":"locality"
},
  "geometry": {"coordinates":[165.63333,-21.43333],"type":"Point"}
}